{"cubeId": "auvezebq", "dimensions": [{"id":"D0","name":"Accounting entry","dimensionItems":[{"id":"N","name":"Net international investment position"},{"id":"A","name":"Assets"},{"id":"P","name":"Liabilities"}]},{"id":"D1","name":"Component","dimensionItems":[{"id":"T","name":"Total"},{"id":"TOD","name":"Total (excluding derivatives)"},{"id":"DI","name":"Direct investment","dimensionItems":[{"id":"DIT","name":"Total"},{"id":"DIBK","name":"Equity capital"},{"id":"DIKR","name":"Debt instruments"}]},{"id":"PFI","name":"Portfolio investment","dimensionItems":[{"id":"PFIT","name":"Total"},{"id":"PFIS","name":"Debt securities","dimensionItems":[{"id":"PFIST","name":"Total"},{"id":"PFISK","name":"Short-term"},{"id":"PFISL","name":"Long-term"}]},{"id":"PFIDP","name":"Equity securities","dimensionItems":[{"id":"PFIDPT","name":"Total"},{"id":"PFIDPA","name":"Shares"},{"id":"PFIDPKA","name":"Collective investment schemes"}]}]},{"id":"D","name":"Derivatives"},{"id":"UI","name":"Other investment","dimensionItems":[{"id":"UIT","name":"Total"},{"id":"UIBE","name":"Currency and deposits","dimensionItems":[{"id":"UIBET","name":"Total"},{"id":"UIBESNB","name":"Swiss National Bank"},{"id":"UIBEB","name":"Banks","dimensionItems":[{"id":"UIBEBT","name":"Total"},{"id":"UIBEBFB","name":"Of which Amounts due from banks"},{"id":"UIBEBVB","name":"Of which Amounts due to banks"},{"id":"UIBEBVK","name":"Of which Amounts due to customers"}]},{"id":"UIBEOH","name":"Public sector"},{"id":"UIBEUS","name":"Other sectors"}]},{"id":"UIK","name":"Loans","dimensionItems":[{"id":"UIKT","name":"Total"},{"id":"UIKSNB","name":"Swiss National Bank"},{"id":"UIKB","name":"Banks","dimensionItems":[{"id":"UIKBT","name":"Total"},{"id":"UIKBFK","name":"Of which Amounts due from customers"}]},{"id":"UIKOH","name":"Public sector"},{"id":"UIKUS","name":"Other sectors"}]},{"id":"UIUA","name":"Other assets"},{"id":"UIUP","name":"Other liabilities"}]},{"id":"WR","name":"Reserve assets","dimensionItems":[{"id":"WRT","name":"Total"},{"id":"WRG","name":"Gold holdings"},{"id":"WRIMF","name":"Reserve position in the IMF"},{"id":"WRSZR","name":"Special Drawing Rights"},{"id":"WRDA","name":"Foreign currency investments","dimensionItems":[{"id":"WRDAT","name":"Total"},{"id":"WRDAWP","name":"Securities"},{"id":"WRDABE","name":"Currency and deposits"}]},{"id":"WRU","name":"Other positions"}]}]},{"id":"D2","name":"Level/Change","dimensionItems":[{"id":"LE1","name":"IIP previous period"},{"id":"X","name":"Changes in stocks","dimensionItems":[{"id":"LX","name":"Total"},{"id":"T","name":"Transactions"},{"id":"NT","name":"Changes in stocks other than transactions","dimensionItems":[{"id":"K","name":"Total"},{"id":"WV","name":"Revaluations","dimensionItems":[{"id":"K7","name":"Total"},{"id":"K7A","name":"Exchange rate changes"},{"id":"K7B","name":"Price changes"}]},{"id":"KA","name":"Other changes in volume"}]}]},{"id":"LE","name":"IIP"}]}]}